rssfixer/__init__.py
rssfixer/rss.py
rssfixer-0.2.16.dist-info/LICENSE
rssfixer-0.2.16.dist-info/METADATA
rssfixer-0.2.16.dist-info/WHEEL
rssfixer-0.2.16.dist-info/entry_points.txt
rssfixer-0.2.16.dist-info/RECORD
