Metadata-Version: 2.3
Name: rssfixer
Version: 0.2.16
Summary: Generate RSS feed for Wordpress blog without it.
License: MIT
Author: Peter Reuterås
Author-email: peter@reuteras.net
Requires-Python: >=3.8
Classifier: Programming Language :: Python :: 3
Classifier: License :: OSI Approved :: MIT License
Classifier: Operating System :: OS Independent
Classifier: Natural Language :: English
Classifier: Intended Audience :: Information Technology
Classifier: Development Status :: 4 - Beta
Classifier: Environment :: Console
Requires-Dist: beautifulsoup4 (>=4.12.3)
Requires-Dist: docutils (>=0.21.2)
Requires-Dist: feedgen (==0.9.0)
Requires-Dist: requests (>=2.32.3)
Project-URL: Bug Tracker, https://github.com/reuteras/rssfixer/issues
Project-URL: Homepage, https://github.com/reuteras/rssfixer
